ezipress-202601210707.dist-info/licenses/LICENSE
src/__init__.py
src/cli.py
src/config.py
src/main.py
src/typing.py
src/archive/__init__.py
src/archive/epub_handler.py
src/archive/marker.py
src/archive/rar_handler.py
src/archive/zip_handler.py
src/compressor/__init__.py
src/compressor/core.py
src/compressor/exceptions.py
src/compressor/strategy.py
src/controller/__init__.py
src/controller/batch_controller.py
src/display/__init__.py
src/display/legacy_output.py
src/utils/__init__.py
src/utils/file_utils.py
src/utils/logger.py
ezipress-202601210707.dist-info/METADATA
ezipress-202601210707.dist-info/WHEEL
ezipress-202601210707.dist-info/entry_points.txt
ezipress-202601210707.dist-info/top_level.txt
ezipress-202601210707.dist-info/RECORD
