Metadata-Version: 2.4
Name: ezipress
Version: 202601210707
Summary: File image re-compression tool - supports ZIP, RAR, EPUB format image compression processing
Author-email: Sam Weng <eyes1971@gmail.com>
Maintainer-email: Sam Weng <eyes1971@gmail.com>
License: MIT
Project-URL: Homepage, https://github.com/eyes1971/ezipress
Project-URL: Documentation, https://ezipress.readthedocs.io/
Project-URL: Repository, https://github.com/eyes1971/ezipress
Project-URL: Bug Tracker, https://github.com/eyes1971/ezipress/issues
Project-URL: Changelog, https://github.com/eyes1971/ezipress/blob/main/CHANGELOG.md
Keywords: compression,image,zip,rar,epub,optimization,batch processing,file processing,image compression,file processing
Classifier: Development Status :: 4 - Beta
Classifier: Environment :: Console
Classifier: Intended Audience :: End Users/Desktop
Classifier: Intended Audience :: Developers
Classifier: License :: OSI Approved :: MIT License
Classifier: Operating System :: OS Independent
Classifier: Programming Language :: Python :: 3
Classifier: Programming Language :: Python :: 3.8
Classifier: Programming Language :: Python :: 3.9
Classifier: Programming Language :: Python :: 3.10
Classifier: Programming Language :: Python :: 3.11
Classifier: Programming Language :: Python :: 3.12
Classifier: Topic :: Multimedia :: Graphics
Classifier: Topic :: System :: Archiving :: Compression
Classifier: Topic :: Utilities
Requires-Python: >=3.8
License-File: LICENSE
Requires-Dist: Pillow>=9.0.0
Requires-Dist: numpy>=1.20.0
Requires-Dist: scikit-fuzzy>=0.4.0
Requires-Dist: colorama>=0.4.0; sys_platform == "win32"
Provides-Extra: dev
Requires-Dist: pytest>=7.0.0; extra == "dev"
Requires-Dist: pytest-cov>=4.0.0; extra == "dev"
Requires-Dist: black>=22.0.0; extra == "dev"
Requires-Dist: isort>=5.10.0; extra == "dev"
Requires-Dist: flake8>=5.0.0; extra == "dev"
Requires-Dist: mypy>=1.0.0; extra == "dev"
Requires-Dist: pre-commit>=2.20.0; extra == "dev"
Provides-Extra: docs
Requires-Dist: sphinx>=5.0.0; extra == "docs"
Requires-Dist: sphinx-rtd-theme>=1.0.0; extra == "docs"
Requires-Dist: myst-parser>=0.18.0; extra == "docs"
Provides-Extra: full
Requires-Dist: rarfile>=4.0; extra == "full"
Requires-Dist: colorama>=0.4.0; extra == "full"
Provides-Extra: windows
Requires-Dist: colorama>=0.4.0; extra == "windows"
Requires-Dist: pywin32>=304; sys_platform == "win32" and extra == "windows"
Provides-Extra: rar
Requires-Dist: rarfile>=4.0; extra == "rar"
Dynamic: license-file
